cache_cleaner/__init__.py
cache_cleaner/admin.py
cache_cleaner/apps.py
cache_cleaner/metadata.py
cache_cleaner/models.py
cache_cleaner/locale/en/LC_MESSAGES/django.mo
cache_cleaner/locale/en/LC_MESSAGES/django.po
cache_cleaner/locale/it/LC_MESSAGES/django.mo
cache_cleaner/locale/it/LC_MESSAGES/django.po
cache_cleaner/management/__init__.py
cache_cleaner/management/commands/__init__.py
cache_cleaner/management/commands/clear_cache.py
cache_cleaner/migrations/0001_initial.py
cache_cleaner/migrations/__init__.py
django_cache_cleaner-0.1.0.dist-info/LICENSE.txt
django_cache_cleaner-0.1.0.dist-info/METADATA
django_cache_cleaner-0.1.0.dist-info/WHEEL
django_cache_cleaner-0.1.0.dist-info/top_level.txt
django_cache_cleaner-0.1.0.dist-info/RECORD
