Metadata-Version: 2.1
Name: django-cache-cleaner
Version: 0.1.0
Summary: clear the entire cache or individual caches easily using the admin panel or management command.
Author-email: Fabio Caccamo <fabio.caccamo@gmail.com>
Maintainer-email: Fabio Caccamo <fabio.caccamo@gmail.com>
License: MIT License
Project-URL: Homepage, https://github.com/fabiocaccamo/django-cache-cleaner
Project-URL: Download, https://github.com/fabiocaccamo/django-cache-cleaner/releases
Project-URL: Documentation, https://github.com/fabiocaccamo/django-cache-cleaner#readme
Project-URL: Issues, https://github.com/fabiocaccamo/django-cache-cleaner/issues
Project-URL: Funding, https://github.com/sponsors/fabiocaccamo/
Project-URL: Twitter, https://twitter.com/fabiocaccamo
Keywords: django,cache,caches,cleaner,clear,clean,cleanup,command,management,purge
Classifier: Development Status :: 5 - Production/Stable
Classifier: Environment :: Web Environment
Classifier: Framework :: Django
Classifier: Framework :: Django :: 3.2
Classifier: Framework :: Django :: 4.0
Classifier: Framework :: Django :: 4.1
Classifier: Framework :: Django :: 4.2
Classifier: Framework :: Django :: 5.0
Classifier: Intended Audience :: Developers
Classifier: License :: OSI Approved :: MIT License
Classifier: Natural Language :: English
Classifier: Operating System :: OS Independent
Classifier: Programming Language :: Python :: 3
Classifier: Programming Language :: Python :: 3.8
Classifier: Programming Language :: Python :: 3.9
Classifier: Programming Language :: Python :: 3.10
Classifier: Programming Language :: Python :: 3.11
Classifier: Programming Language :: Python :: 3.12
Classifier: Topic :: Software Development :: Build Tools
License-File: LICENSE.txt
